data_quality_tests/__init__.py
data_quality_tests/dq.py
data_quality_tests-3.1.1.dist-info/METADATA
data_quality_tests-3.1.1.dist-info/WHEEL
data_quality_tests-3.1.1.dist-info/top_level.txt
data_quality_tests-3.1.1.dist-info/RECORD
